embypy/__init__.py
embypy/__main__.py
embypy/emby.py
embypy/objects/__init__.py
embypy/objects/folders.py
embypy/objects/misc.py
embypy/objects/object.py
embypy/objects/videos.py
embypy/utils/__init__.py
embypy/utils/asyncio.py
embypy/utils/connector.py
embypyfix-0.6.6.4.dist-info/LICENSE.txt
embypyfix-0.6.6.4.dist-info/METADATA
embypyfix-0.6.6.4.dist-info/WHEEL
embypyfix-0.6.6.4.dist-info/top_level.txt
embypyfix-0.6.6.4.dist-info/RECORD
