Metadata-Version: 2.1
Name: embypyfix
Version: 0.6.6.4
Summary: Python API wrapper for Emby Media Browser
Home-page: https://pypi.org/project/EmbyPy/
Author: Andriy Zasypkin
Author-email: AndriyZasypkin@gmail.com
License: LGPLv3
Keywords: Emby MediaBrowser API
Classifier: Development Status :: 4 - Beta
Classifier: Framework :: AsyncIO
Classifier: Intended Audience :: Developers
Classifier: Topic :: Software Development :: Libraries :: Python Modules
Classifier: License :: OSI Approved :: GNU Lesser General Public License v3 (LGPLv3)
License-File: LICENSE.txt
Requires-Dist: aiohttp
Requires-Dist: arrow
Requires-Dist: requests
Requires-Dist: simplejson
Requires-Dist: websockets
